{"nm":"scene1","ddd":0,"h":500,"w":500,"meta":{"g":"@lottiefiles/creator 0.48.0"},"layers":[{"ty":4,"nm":"Shape Layer - SVG","sr":1,"st":0,"op":150,"ip":0,"hd":false,"ddd":0,"bm":0,"hasMask":false,"ao":0,"ks":{"a":{"a":0,"k":[32,34.5]},"s":{"a":0,"k":[405.0344462109173,405.0344462109173]},"sk":{"a":0,"k":0},"p":{"a":0,"k":[250,252.5]},"r":{"a":0,"k":0},"sa":{"a":0,"k":0},"o":{"a":1,"k":[{"o":{"x":0.167,"y":0.167},"i":{"x":0.833,"y":0.833},"s":[0],"t":0},{"s":[100],"t":30}]}},"ef":[],"shapes":[{"ty":"gr","bm":0,"hd":false,"nm":"Group 1","it":[{"ty":"el","bm":0,"hd":false,"nm":"Ellipse 1","d":1,"p":{"a":0,"k":[44,37]},"s":{"a":0,"k":[8,8]}},{"ty":"fl","bm":0,"hd":false,"nm":"Fill","c":{"a":0,"k":[0.6118,0.2039,0.7608]},"r":1,"o":{"a":0,"k":100}},{"ty":"tr","a":{"a":0,"k":[0,0]},"s":{"a":0,"k":[100,100]},"sk":{"a":0,"k":0},"p":{"a":0,"k":[0,0]},"r":{"a":0,"k":0},"sa":{"a":0,"k":0},"o":{"a":0,"k":100}}]},{"ty":"gr","bm":0,"hd":false,"nm":"Group 2","it":[{"ty":"el","bm":0,"hd":false,"nm":"Ellipse 2","d":1,"p":{"a":0,"k":[20,37]},"s":{"a":0,"k":[8,8]}},{"ty":"fl","bm":0,"hd":false,"nm":"Fill","c":{"a":0,"k":[0.6118,0.2039,0.7608]},"r":1,"o":{"a":0,"k":100}},{"ty":"tr","a":{"a":0,"k":[20.000000000000004,37]},"s":{"a":0,"k":[100,100]},"sk":{"a":0,"k":0},"p":{"a":0,"k":[20.000000000000004,37]},"r":{"a":0,"k":0},"sa":{"a":0,"k":0},"o":{"a":0,"k":100}}]},{"ty":"gr","bm":0,"hd":false,"nm":"Group 3","it":[{"ty":"sh","bm":0,"hd":false,"nm":"Path 1","d":1,"ks":{"a":0,"k":{"c":true,"i":[[0,0],[0,0.8279999999999994],[0,0],[-1.9299999999999997,0],[0,0],[0,-0.8279999999999994],[0.8279999999999994,0],[0,0],[0,-0.2749999999999986],[0,0],[0.8279999999999994,0]],"o":[[-0.8279999999999994,0],[0,0],[0,-1.9299999999999997],[0,0],[0.8279999999999994,0],[0,0.8279999999999994],[0,0],[-0.27500000000000036,0],[0,0],[0,0.8279999999999994],[0,0]],"v":[[14,31],[12.5,29.5],[12.5,25],[16,21.5],[21.5,21.5],[23,23],[21.5,24.5],[16,24.5],[15.5,25],[15.5,29.5],[14,31]]}}},{"ty":"fl","bm":0,"hd":false,"nm":"Fill","c":{"a":0,"k":[1,1,1]},"r":1,"o":{"a":0,"k":100}},{"ty":"tr","a":{"a":0,"k":[17.75000000000001,26.250000000000004]},"s":{"a":0,"k":[100,100]},"sk":{"a":0,"k":0},"p":{"a":0,"k":[17.75000000000001,26.250000000000004]},"r":{"a":0,"k":0},"sa":{"a":0,"k":0},"o":{"a":0,"k":100}}]},{"ty":"gr","bm":0,"hd":false,"nm":"Group 4","it":[{"ty":"sh","bm":0,"hd":false,"nm":"Path 2","d":1,"ks":{"a":0,"k":{"c":true,"i":[[0,0],[0,0],[0,-2.761000000000003],[0,0],[0.5510000000000019,0],[0,0],[0,-2.761000000000003],[0,0],[0,3.314]],"o":[[0,0],[-2.761000000000003,0],[0,0],[0,0.5510000000000019],[0,0],[-2.7609999999999992,0],[0,0],[3.314,0],[0,0]],"v":[[54,48],[54,31],[49,36],[49,48],[48,49],[31,49],[26,54],[48,54],[54,48]]}}},{"ty":"fl","bm":0,"hd":false,"nm":"Fill","c":{"a":0,"k":[0,0,0]},"r":1,"o":{"a":0,"k":100}},{"ty":"tr","a":{"a":0,"k":[40.000000000000014,42.500000000000014]},"s":{"a":0,"k":[100,100]},"sk":{"a":0,"k":0},"p":{"a":0,"k":[40.000000000000014,42.500000000000014]},"r":{"a":0,"k":0},"sa":{"a":0,"k":0},"o":{"a":0,"k":15}}]},{"ty":"gr","bm":0,"hd":false,"nm":"Group 5","it":[{"ty":"sh","bm":0,"hd":false,"nm":"Path 3","d":1,"ks":{"a":0,"k":{"c":true,"i":[[0,0],[0,2.7609999999999992],[0,0],[0,-3.314],[0,0],[0,2.761000000000003],[0,0],[-0.5510000000000002,0],[0,0]],"o":[[2.761000000000003,0],[0,0],[-3.314,0],[0,0],[2.7609999999999992,0],[0,0],[0,-0.5509999999999984],[0,0],[0,0]],"v":[[30,24],[35,19],[16,19],[10,25],[10,43],[15,38],[15,25],[16,24],[30,24]]}}},{"ty":"fl","bm":0,"hd":false,"nm":"Fill","c":{"a":0,"k":[1,1,1]},"r":1,"o":{"a":0,"k":100}},{"ty":"tr","a":{"a":0,"k":[22.500000000000004,31.000000000000004]},"s":{"a":0,"k":[100,100]},"sk":{"a":0,"k":0},"p":{"a":0,"k":[22.500000000000004,31.000000000000004]},"r":{"a":0,"k":0},"sa":{"a":0,"k":0},"o":{"a":0,"k":30}}]},{"ty":"gr","bm":0,"hd":false,"nm":"Group 6","it":[{"ty":"el","bm":0,"hd":false,"nm":"Ellipse 3","d":1,"p":{"a":0,"k":[32,37]},"s":{"a":0,"k":[8,8]}},{"ty":"fl","bm":0,"hd":false,"nm":"Fill","c":{"a":0,"k":[0.6118,0.2039,0.7608]},"r":1,"o":{"a":0,"k":100}},{"ty":"tr","a":{"a":0,"k":[32,37]},"s":{"a":0,"k":[100,100]},"sk":{"a":0,"k":0},"p":{"a":0,"k":[32,37]},"r":{"a":0,"k":0},"sa":{"a":0,"k":0},"o":{"a":0,"k":100}}]},{"ty":"gr","bm":0,"hd":false,"nm":"Group 7","it":[{"ty":"sh","bm":0,"hd":false,"nm":"Path 4","d":1,"ks":{"a":0,"k":{"c":true,"i":[[0,0],[0,0],[0,-3.314],[0,0],[-3.314,0],[0,0],[0,3.314],[0,0],[3.314,0]],"o":[[0,0],[-3.314,0],[0,0],[0,3.314],[0,0],[3.314,0],[0,0],[0,-3.314],[0,0]],"v":[[48,19],[16,19],[10,25],[10,48],[16,54],[48,54],[54,48],[54,25],[48,19]]}}},{"ty":"fl","bm":0,"hd":false,"nm":"Fill","c":{"a":0,"k":[1,0.6471,0]},"r":1,"o":{"a":0,"k":100}},{"ty":"tr","a":{"a":0,"k":[32,36.500000000000014]},"s":{"a":0,"k":[100,100]},"sk":{"a":0,"k":0},"p":{"a":0,"k":[32,36.500000000000014]},"r":{"a":0,"k":0},"sa":{"a":0,"k":0},"o":{"a":0,"k":100}}]},{"ty":"gr","bm":0,"hd":false,"nm":"Group 8","it":[{"ty":"el","bm":0,"hd":false,"nm":"Ellipse 4","d":1,"p":{"a":0,"k":[32,61]},"s":{"a":0,"k":[38,6]}},{"ty":"fl","bm":0,"hd":false,"nm":"Fill","c":{"a":0,"k":[0.6588,0.6588,0.6588]},"r":1,"o":{"a":0,"k":100}},{"ty":"tr","a":{"a":0,"k":[32,61.000000000000014]},"s":{"a":1,"k":[{"o":{"x":0.167,"y":0.167},"i":{"x":0.833,"y":0.833},"s":[65.57934253246749,65.57934253246749],"t":0},{"s":[100,100],"t":60}]},"sk":{"a":0,"k":0},"p":{"a":0,"k":[32,61.000000000000014]},"r":{"a":0,"k":0},"sa":{"a":0,"k":0},"o":{"a":0,"k":100}}]},{"ty":"gr","bm":0,"hd":false,"nm":"Group 9","it":[{"ty":"sh","bm":0,"hd":false,"nm":"Path 5","d":1,"ks":{"a":0,"k":{"c":true,"i":[[0,0],[0,0],[0,0],[3.8590000000000018,0],[0,-3.859],[0,0],[0,0],[0,0],[-7.167999999999999,0],[0,-7.167999999999999],[0,0]],"o":[[0,0],[0,0],[0,-3.859],[-3.8590000000000018,0],[0,0],[0,0],[0,0],[0,-7.167999999999999],[7.167999999999999,0],[0,0],[0,0]],"v":[[45,22],[39,22],[39,18],[32,11],[25,18],[25,22],[19,22],[19,18],[32,5],[45,18],[45,22]]}}},{"ty":"fl","bm":0,"hd":false,"nm":"Fill","c":{"a":0,"k":[0.6118,0.2039,0.7608]},"r":1,"o":{"a":0,"k":100}},{"ty":"tr","a":{"a":0,"k":[32,13.500000000000004]},"s":{"a":0,"k":[100,100]},"sk":{"a":0,"k":0},"p":{"a":1,"k":[{"o":{"x":0.167,"y":0.167},"i":{"x":0.833,"y":0.833},"s":[32,9.500000000000004],"t":0},{"s":[32,12.500000000000004],"t":60}]},"r":{"a":0,"k":0},"sa":{"a":0,"k":0},"o":{"a":0,"k":100}}]}],"ind":1}],"v":"5.7.0","fr":30,"op":60,"ip":0,"assets":[]}